diff_files/__init__.py
diff_files/cli.py
diff_files-0.1.1.dist-info/entry_points.txt
diff_files-0.1.1.dist-info/WHEEL
diff_files-0.1.1.dist-info/METADATA
diff_files-0.1.1.dist-info/RECORD
